README.md
setup.py
sasrunner/__init__.py
sasrunner.egg-info/PKG-INFO
sasrunner.egg-info/SOURCES.txt
sasrunner.egg-info/dependency_links.txt
sasrunner.egg-info/requires.txt
sasrunner.egg-info/top_level.txt