Metadata-Version: 1.0
Name: sasrunner
Version: 0.1
Summary: SAS runner
Home-page: https://wrds-web.wharton.upenn.edu/wrds/
Author: Joe Dougherty
Author-email: josepd@wharton.upenn.edu
License: UNKNOWN
Keywords: SAS,etl
Platform: UNKNOWN
